gcp_impersonation_wrapper/__init__.py
gcp_impersonation_wrapper/impersonated_service_account.py
gcp_impersonation_wrapper/service_account.py
gcp_impersonation_wrapper-0.0.6.dist-info/METADATA
gcp_impersonation_wrapper-0.0.6.dist-info/WHEEL
gcp_impersonation_wrapper-0.0.6.dist-info/top_level.txt
gcp_impersonation_wrapper-0.0.6.dist-info/RECORD
